MANIFEST.in
README.md
setup.cfg
setup.py
octomap/dynamicEDT3D_defs.pxd
octomap/include_and_setting.h
octomap/octomap.pyx
octomap/octomap_defs.pxd
octomap_python_messy.egg-info/PKG-INFO
octomap_python_messy.egg-info/SOURCES.txt
octomap_python_messy.egg-info/dependency_links.txt
octomap_python_messy.egg-info/requires.txt
octomap_python_messy.egg-info/top_level.txt
src/octomap/.git
src/octomap/.gitignore
src/octomap/.travis.yml
src/octomap/CMakeLists.txt
src/octomap/README.md
src/octomap/increase_version.py
src/octomap/dynamicEDT3D/CHANGELOG.txt
src/octomap/dynamicEDT3D/CMakeLists.txt
src/octomap/dynamicEDT3D/LICENSE.txt
src/octomap/dynamicEDT3D/README.txt
src/octomap/dynamicEDT3D/doxygen.h
src/octomap/dynamicEDT3D/dynamicEDT3D.dox
src/octomap/dynamicEDT3D/dynamicEDT3DConfig-version.cmake.in
src/octomap/dynamicEDT3D/dynamicEDT3DConfig.cmake.in
src/octomap/dynamicEDT3D/package.xml
src/octomap/dynamicEDT3D/CMakeModules/CMakeUninstall.cmake.in
src/octomap/dynamicEDT3D/CMakeModules/CPackSettings.cmake
src/octomap/dynamicEDT3D/CMakeModules/CompilerSettings.cmake
src/octomap/dynamicEDT3D/CMakeModules/InstallPkgConfigFile.cmake
src/octomap/dynamicEDT3D/include/dynamicEDT3D/bucketedqueue.h
src/octomap/dynamicEDT3D/include/dynamicEDT3D/bucketedqueue.hxx
src/octomap/dynamicEDT3D/include/dynamicEDT3D/dynamicEDT3D.h
src/octomap/dynamicEDT3D/include/dynamicEDT3D/dynamicEDTOctomap.h
src/octomap/dynamicEDT3D/include/dynamicEDT3D/point.h
src/octomap/dynamicEDT3D/src/CMakeLists.txt
src/octomap/dynamicEDT3D/src/dynamicEDT3D.cpp
src/octomap/dynamicEDT3D/src/dynamicEDTOctomap.cpp
src/octomap/dynamicEDT3D/src/examples/CMakeLists.txt
src/octomap/dynamicEDT3D/src/examples/exampleEDT3D.cpp
src/octomap/dynamicEDT3D/src/examples/exampleEDTOctomap.cpp
src/octomap/octomap/AUTHORS.txt
src/octomap/octomap/CHANGELOG.txt
src/octomap/octomap/CMakeLists.txt
src/octomap/octomap/LICENSE.txt
src/octomap/octomap/README.md
src/octomap/octomap/doxygen.h
src/octomap/octomap/octomap-config-version.cmake.in
src/octomap/octomap/octomap-config.cmake.in
src/octomap/octomap/octomap.dox.in
src/octomap/octomap/package.xml
src/octomap/octomap/valgrind_memcheck.supp
src/octomap/octomap/CMakeModules/CMakeUninstall.cmake.in
