Metadata-Version: 2.1
Name: octomap-python-messy
Version: 1.8.0.post12.dev0
Summary: Python binding of the OctoMap library.
Home-page: https://github.com/HiroIshida/octomap-python
Maintainer: Hirokazu Ishida
Maintainer-email: h-ishida@jsk.imi.i.u-tokyo.ac.jp
License: BSD
Classifier: Development Status :: 5 - Production/Stable
Classifier: Intended Audience :: Developers
Classifier: Natural Language :: English
Classifier: Programming Language :: Python
Classifier: Programming Language :: Python :: 2
Classifier: Programming Language :: Python :: 3
Classifier: Programming Language :: Python :: Implementation :: CPython
Classifier: Programming Language :: Python :: Implementation :: PyPy
Provides-Extra: example
